mlcvzoo_tracker/__init__.py
mlcvzoo_tracker/annotation_utils.py
mlcvzoo_tracker/configuration.py
mlcvzoo_tracker/hungarian_image_tracker.py
mlcvzoo_tracker/image_track.py
mlcvzoo_tracker/py.typed
mlcvzoo_tracker/sized_dict.py
mlcvzoo_tracker/types.py
mlcvzoo_tracker-2.2.0.dist-info/LICENSE
mlcvzoo_tracker-2.2.0.dist-info/METADATA
mlcvzoo_tracker-2.2.0.dist-info/WHEEL
mlcvzoo_tracker-2.2.0.dist-info/top_level.txt
mlcvzoo_tracker-2.2.0.dist-info/RECORD
